{"coord":{"lon":4.9,"lat":52.36},"weather":[{"id":310,"main":"Drizzle","description":"light intensity drizzle rain","icon":"09n"},{"id":501,"main":"Rain","description":"moderate rain","icon":"10n"}],"base":"stations","main":{"temp":3.65,"feels_like":-1.83,"temp_min":3.28,"temp_max":4.45,"pressure":994,"humidity":88,"sea_level":994,"grnd_level":994},"visibility":6000,"wind":{"speed":8.75,"deg":140,"gust":14.4},"rain":{"1h":2.73},"clouds":{"all":75},"dt":1737923279,"sys":{"type":2,"id":2016069,"country":"NL","sunrise":1737876625,"sunset":1737908114},"timezone":3600,"id":7648382,"name":"Weesperzijde","cod":200}