{"coord":{"lon":4.9,"lat":52.36},"weather":[{"id":520,"main":"Rain","description":"light intensity shower rain","icon":"09d"}],"base":"stations","main":{"temp":9.04,"feels_like":5.23,"temp_min":8.28,"temp_max":9.96,"pressure":1000,"humidity":75,"sea_level":1000,"grnd_level":1001},"visibility":5000,"wind":{"speed":8.75,"deg":300,"gust":14.4},"rain":{"1h":0.24},"clouds":{"all":75},"dt":1761460939,"sys":{"type":2,"id":2101578,"country":"NL","sunrise":1761459914,"sunset":1761495794},"timezone":3600,"id":2759793,"name":"Gemeente Amsterdam","cod":200}