{"coord":{"lon":4.9,"lat":52.36},"weather":[{"id":701,"main":"Mist","description":"mist","icon":"50n"}],"base":"stations","main":{"temp":-0.45,"feels_like":-3.74,"temp_min":-1.17,"temp_max":0.53,"pressure":1025,"humidity":91,"sea_level":1025,"grnd_level":1025},"visibility":3000,"wind":{"speed":2.68,"deg":162,"gust":3.58},"clouds":{"all":75},"dt":1737257558,"sys":{"type":2,"id":2016069,"country":"NL","sunrise":1737272341,"sunset":1737302572},"timezone":3600,"id":7648382,"name":"Weesperzijde","cod":200}