{"coord":{"lon":4.9,"lat":52.36},"weather":[{"id":800,"main":"Clear","description":"clear sky","icon":"01d"}],"base":"stations","main":{"temp":16.57,"feels_like":15.88,"temp_min":15.48,"temp_max":17.74,"pressure":1020,"humidity":61,"sea_level":1020,"grnd_level":1020},"visibility":10000,"wind":{"speed":3.13,"deg":356,"gust":3.13},"clouds":{"all":0},"dt":1747478148,"sys":{"type":2,"id":2016069,"country":"NL","sunrise":1747453316,"sunset":1747510313},"timezone":7200,"id":7648382,"name":"Weesperzijde","cod":200}