{"coord":{"lon":4.9,"lat":52.36},"weather":[{"id":310,"main":"Drizzle","description":"light intensity drizzle rain","icon":"09d"},{"id":501,"main":"Rain","description":"moderate rain","icon":"10d"}],"base":"stations","main":{"temp":10.92,"feels_like":10,"temp_min":10.5,"temp_max":11.62,"pressure":1015,"humidity":74,"sea_level":1015,"grnd_level":1015},"visibility":10000,"wind":{"speed":8.23,"deg":190},"rain":{"1h":1.33},"clouds":{"all":75},"dt":1740379221,"sys":{"type":2,"id":2012552,"country":"NL","sunrise":1740379064,"sunset":1740416990},"timezone":3600,"id":7648382,"name":"Weesperzijde","cod":200}