{"coord":{"lon":4.9,"lat":52.36},"weather":[{"id":800,"main":"Clear","description":"clear sky","icon":"01d"}],"base":"stations","main":{"temp":19.83,"feels_like":19.57,"temp_min":18.29,"temp_max":21.62,"pressure":1025,"humidity":65,"sea_level":1025,"grnd_level":1025},"visibility":10000,"wind":{"speed":1.79,"deg":6,"gust":3.13},"clouds":{"all":0},"dt":1754897908,"sys":{"type":2,"id":2101578,"country":"NL","sunrise":1754885819,"sunset":1754939661},"timezone":7200,"id":7648382,"name":"Weesperzijde","cod":200}