{"coord":{"lon":4.9,"lat":52.36},"weather":[{"id":500,"main":"Rain","description":"light rain","icon":"10n"}],"base":"stations","main":{"temp":12.27,"feels_like":12.03,"temp_min":12.27,"temp_max":12.27,"pressure":1002,"humidity":95,"sea_level":1002,"grnd_level":1002},"visibility":9982,"wind":{"speed":8.64,"deg":184,"gust":19.69},"rain":{"1h":0.75},"clouds":{"all":100},"dt":1759530602,"sys":{"country":"NL","sunrise":1759556788,"sunset":1759597891},"timezone":7200,"id":7648382,"name":"Weesperzijde","cod":200}