{"coord":{"lon":4.9,"lat":52.36},"weather":[{"id":801,"main":"Clouds","description":"few clouds","icon":"02n"}],"base":"stations","main":{"temp":11.59,"feels_like":10.92,"temp_min":11.59,"temp_max":11.59,"pressure":1025,"humidity":81,"sea_level":1025,"grnd_level":1025},"visibility":10000,"wind":{"speed":1.83,"deg":109,"gust":1.97},"clouds":{"all":18},"dt":1772647058,"sys":{"country":"NL","sunrise":1772605238,"sunset":1772645041},"timezone":3600,"id":2759793,"name":"Gemeente Amsterdam","cod":200}