{"coord":{"lon":4.9,"lat":52.36},"weather":[{"id":520,"main":"Rain","description":"light intensity shower rain","icon":"09d"}],"base":"stations","main":{"temp":15.45,"feels_like":15.01,"temp_min":14.37,"temp_max":18.29,"pressure":997,"humidity":75,"sea_level":997,"grnd_level":997},"visibility":8000,"wind":{"speed":9.26,"deg":260},"rain":{"1h":0.11},"clouds":{"all":75},"dt":1744731216,"sys":{"type":2,"id":2016505,"country":"NL","sunrise":1744692156,"sunset":1744742267},"timezone":7200,"id":7648382,"name":"Weesperzijde","cod":200}