{"coord":{"lon":4.9,"lat":52.36},"weather":[{"id":500,"main":"Rain","description":"light rain","icon":"10n"}],"base":"stations","main":{"temp":14.35,"feels_like":14.16,"temp_min":13.84,"temp_max":15.01,"pressure":1003,"humidity":89,"sea_level":1003,"grnd_level":1003},"visibility":9000,"wind":{"speed":8.75,"deg":210},"rain":{"1h":0.27},"clouds":{"all":75},"dt":1727721447,"sys":{"type":2,"id":2016069,"country":"NL","sunrise":1727674808,"sunset":1727716818},"timezone":7200,"id":7648382,"name":"Weesperzijde","cod":200}