{"coord":{"lon":4.9,"lat":52.36},"weather":[{"id":801,"main":"Clouds","description":"few clouds","icon":"02n"}],"base":"stations","main":{"temp":11.33,"feels_like":10.97,"temp_min":10.5,"temp_max":12.23,"pressure":1001,"humidity":94,"sea_level":1001,"grnd_level":1001},"visibility":9000,"wind":{"speed":2.57,"deg":150},"clouds":{"all":20},"dt":1744756435,"sys":{"type":2,"id":2046553,"country":"NL","sunrise":1744778424,"sunset":1744828771},"timezone":7200,"id":7648382,"name":"Weesperzijde","cod":200}