{"coord":{"lon":4.9,"lat":52.36},"weather":[{"id":801,"main":"Clouds","description":"few clouds","icon":"02n"}],"base":"stations","main":{"temp":12.71,"feels_like":11.79,"temp_min":11.7,"temp_max":13.34,"pressure":1016,"humidity":67,"sea_level":1016,"grnd_level":1016},"visibility":10000,"wind":{"speed":6.17,"deg":300},"clouds":{"all":20},"dt":1759689430,"sys":{"type":2,"id":2101578,"country":"NL","sunrise":1759643290,"sunset":1759684152},"timezone":7200,"id":7648382,"name":"Weesperzijde","cod":200}