{"coord":{"lon":4.9,"lat":52.36},"weather":[{"id":801,"main":"Clouds","description":"few clouds","icon":"02d"}],"base":"stations","main":{"temp":19.12,"feels_like":18.34,"temp_min":17.73,"temp_max":20.57,"pressure":1025,"humidity":48,"sea_level":1025,"grnd_level":1025},"visibility":10000,"wind":{"speed":2.06,"deg":70},"clouds":{"all":20},"dt":1745753151,"sys":{"type":2,"id":2012552,"country":"NL","sunrise":1745727429,"sunset":1745780318},"timezone":7200,"id":7648382,"name":"Weesperzijde","cod":200}