{"coord":{"lon":4.9,"lat":52.36},"weather":[{"id":802,"main":"Clouds","description":"scattered clouds","icon":"03n"}],"base":"stations","main":{"temp":22.89,"feels_like":23.4,"temp_min":22.16,"temp_max":23.85,"pressure":1018,"humidity":83,"sea_level":1018,"grnd_level":1018},"visibility":10000,"wind":{"speed":2.68,"deg":118,"gust":4.02},"clouds":{"all":25},"dt":1782427642,"sys":{"type":2,"id":2012552,"country":"NL","sunrise":1782443978,"sunset":1782504396},"timezone":7200,"id":2759793,"name":"Gemeente Amsterdam","cod":200}