{"coord":{"lon":4.9,"lat":52.36},"weather":[{"id":311,"main":"Drizzle","description":"drizzle rain","icon":"09n"},{"id":501,"main":"Rain","description":"moderate rain","icon":"10n"}],"base":"stations","main":{"temp":10.55,"feels_like":10.04,"temp_min":9.95,"temp_max":11.12,"pressure":1002,"humidity":91,"sea_level":1002,"grnd_level":1002},"visibility":4500,"wind":{"speed":6.69,"deg":150},"rain":{"1h":1.22},"clouds":{"all":75},"dt":1765125447,"sys":{"type":2,"id":2101578,"country":"NL","sunrise":1765092957,"sunset":1765121289},"timezone":3600,"id":7648382,"name":"Weesperzijde","cod":200}