{"coord":{"lon":4.9,"lat":52.36},"weather":[{"id":801,"main":"Clouds","description":"few clouds","icon":"02d"}],"base":"stations","main":{"temp":16.57,"feels_like":16.06,"temp_min":15.51,"temp_max":17.75,"pressure":1013,"humidity":68,"sea_level":1013,"grnd_level":1014},"visibility":10000,"wind":{"speed":3.58,"deg":179,"gust":6.71},"clouds":{"all":24},"dt":1762347676,"sys":{"type":2,"id":2101578,"country":"NL","sunrise":1762325015,"sunset":1762358662},"timezone":3600,"id":7648382,"name":"Weesperzijde","cod":200}