{"coord":{"lon":4.9,"lat":52.36},"weather":[{"id":801,"main":"Clouds","description":"few clouds","icon":"02d"}],"base":"stations","main":{"temp":22.95,"feels_like":22.95,"temp_min":21.62,"temp_max":23.9,"pressure":1006,"humidity":63,"sea_level":1006,"grnd_level":1006},"visibility":10000,"wind":{"speed":2.68,"deg":239,"gust":4.02},"clouds":{"all":20},"dt":1756315853,"sys":{"type":2,"id":2101578,"country":"NL","sunrise":1756269813,"sunset":1756320044},"timezone":7200,"id":7648382,"name":"Weesperzijde","cod":200}