{"coord":{"lon":4.9,"lat":52.36},"weather":[{"id":800,"main":"Clear","description":"clear sky","icon":"01d"}],"base":"stations","main":{"temp":35.27,"feels_like":36.83,"temp_min":33.28,"temp_max":37.23,"pressure":1013,"humidity":37,"sea_level":1013,"grnd_level":1012},"visibility":10000,"wind":{"speed":3.6,"deg":180},"clouds":{"all":0},"dt":1751380481,"sys":{"type":2,"id":2016069,"country":"NL","sunrise":1751340159,"sunset":1751400335},"timezone":7200,"id":7648382,"name":"Weesperzijde","cod":200}