{"coord":{"lon":4.9,"lat":52.36},"weather":[{"id":801,"main":"Clouds","description":"few clouds","icon":"02n"}],"base":"stations","main":{"temp":0.31,"feels_like":-3.98,"temp_min":-0.59,"temp_max":1.08,"pressure":1013,"humidity":90,"sea_level":1013,"grnd_level":1013},"visibility":10000,"wind":{"speed":4.12,"deg":360},"clouds":{"all":20},"dt":1767655994,"sys":{"type":2,"id":2101578,"country":"NL","sunrise":1767685741,"sunset":1767714173},"timezone":3600,"id":2759793,"name":"Gemeente Amsterdam","cod":200}