{"coord":{"lon":4.9,"lat":52.36},"weather":[{"id":803,"main":"Clouds","description":"broken clouds","icon":"04n"}],"base":"stations","main":{"temp":2.35,"feels_like":2.35,"temp_min":1.62,"temp_max":3.34,"pressure":1042,"humidity":86,"sea_level":1042,"grnd_level":1042},"visibility":10000,"wind":{"speed":0.45,"deg":149,"gust":0.89},"clouds":{"all":79},"dt":1738812778,"sys":{"type":2,"id":2046553,"country":"NL","sunrise":1738825990,"sunset":1738859750},"timezone":3600,"id":7648382,"name":"Weesperzijde","cod":200}