{"coord":{"lon":4.9,"lat":52.36},"weather":[{"id":801,"main":"Clouds","description":"few clouds","icon":"02d"}],"base":"stations","main":{"temp":6.12,"feels_like":2.05,"temp_min":5.5,"temp_max":7.25,"pressure":1014,"humidity":73,"sea_level":1014,"grnd_level":1014},"visibility":10000,"wind":{"speed":6.71,"deg":248,"gust":8.49},"clouds":{"all":20},"dt":1763470906,"sys":{"type":2,"id":2101578,"country":"NL","sunrise":1763449624,"sunset":1763480663},"timezone":3600,"id":7648382,"name":"Weesperzijde","cod":200}