{"coord":{"lon":4.9,"lat":52.36},"weather":[{"id":801,"main":"Clouds","description":"few clouds","icon":"02d"}],"base":"stations","main":{"temp":21.73,"feels_like":21.63,"temp_min":20.5,"temp_max":23.3,"pressure":1021,"humidity":64,"sea_level":1021,"grnd_level":1021},"visibility":10000,"wind":{"speed":6.17,"deg":290},"clouds":{"all":20},"dt":1754753582,"sys":{"type":2,"id":2101578,"country":"NL","sunrise":1754712822,"sunset":1754767092},"timezone":7200,"id":7648382,"name":"Weesperzijde","cod":200}