{"coord":{"lon":4.9,"lat":52.36},"weather":[{"id":310,"main":"Drizzle","description":"light intensity drizzle rain","icon":"09d"},{"id":500,"main":"Rain","description":"light rain","icon":"10d"}],"base":"stations","main":{"temp":18.94,"feels_like":18.87,"temp_min":16.61,"temp_max":21.2,"pressure":1014,"humidity":76},"visibility":10000,"wind":{"speed":5.36,"deg":189,"gust":5.81},"rain":{"1h":0.2},"clouds":{"all":75},"dt":1716722574,"sys":{"type":2,"id":2012552,"country":"NL","sunrise":1716694204,"sunset":1716752714},"timezone":7200,"id":7648382,"name":"Weesperzijde","cod":200}