{"coord":{"lon":4.9,"lat":52.36},"weather":[{"id":802,"main":"Clouds","description":"scattered clouds","icon":"03d"}],"base":"stations","main":{"temp":14.83,"feels_like":14.2,"temp_min":14.39,"temp_max":15.57,"pressure":1017,"humidity":70,"sea_level":1017,"grnd_level":1017},"visibility":10000,"wind":{"speed":8.49,"deg":184,"gust":9.83},"clouds":{"all":40},"dt":1762252886,"sys":{"type":2,"id":2101578,"country":"NL","sunrise":1762238505,"sunset":1762272368},"timezone":3600,"id":7648382,"name":"Weesperzijde","cod":200}