{"coord":{"lon":4.9,"lat":52.36},"weather":[{"id":803,"main":"Clouds","description":"broken clouds","icon":"04n"}],"base":"stations","main":{"temp":4.25,"feels_like":-0.13,"temp_min":3.27,"temp_max":4.97,"pressure":1029,"humidity":87,"sea_level":1029,"grnd_level":1029},"visibility":7000,"wind":{"speed":6.17,"deg":220},"clouds":{"all":75},"dt":1738720403,"sys":{"type":2,"id":2016069,"country":"NL","sunrise":1738739693,"sunset":1738773236},"timezone":3600,"id":7648382,"name":"Weesperzijde","cod":200}