{"coord":{"lon":4.9,"lat":52.36},"weather":[{"id":802,"main":"Clouds","description":"scattered clouds","icon":"03d"}],"base":"stations","main":{"temp":14.86,"feels_like":14.52,"temp_min":13.85,"temp_max":16.14,"pressure":1011,"humidity":81,"sea_level":1011,"grnd_level":1011},"visibility":10000,"wind":{"speed":9.77,"deg":210},"clouds":{"all":40},"dt":1757666220,"sys":{"type":2,"id":2101578,"country":"NL","sunrise":1757653796,"sunset":1757700223},"timezone":7200,"id":7648382,"name":"Weesperzijde","cod":200}