{"coord":{"lon":4.9,"lat":52.36},"weather":[{"id":801,"main":"Clouds","description":"few clouds","icon":"02d"}],"base":"stations","main":{"temp":21.12,"feels_like":21.04,"temp_min":19.36,"temp_max":22.81,"pressure":1019,"humidity":67,"sea_level":1019,"grnd_level":1019},"visibility":10000,"wind":{"speed":7.72,"deg":230},"clouds":{"all":20},"dt":1748609945,"sys":{"type":2,"id":2012552,"country":"NL","sunrise":1748575577,"sunset":1748634598},"timezone":7200,"id":7648382,"name":"Weesperzijde","cod":200}